Metadata-Version: 1.0
Name: MakeItSo
Version: 0.6.1
Summary: filesystem template interpreter
Home-page: http://k0s.org/hg/MakeItSo
Author: Jeff Hammel
Author-email: k0scist@gmail.com
License: MPL
Keywords: templates
Platform: UNKNOWN
